xiaolu_tool/DBHelper.py
xiaolu_tool/MongoBase.py
xiaolu_tool/__init__.py
xiaolu_tool/commonKit.py
xiaolu_tool/conf.py
xiaolu_tool/dingding_send.py
xiaolu_tool/log.py
xiaolu_tool/orm_base.py
xiaolu_tool/path.py
xiaolu_tool/records.py
xiaolu_tool/thriftKit.py
xiaolu_tool-0.1.0.dist-info/LICENSE
xiaolu_tool-0.1.0.dist-info/METADATA
xiaolu_tool-0.1.0.dist-info/WHEEL
xiaolu_tool-0.1.0.dist-info/top_level.txt
xiaolu_tool-0.1.0.dist-info/RECORD
