Metadata-Version: 2.1
Name: xiaolu_tool
Version: 0.1.0
Summary: A tool for xiaolu data server
Author: xiaolu-developer
Author-email: jiaboyu@xiaoluyy.com
Classifier: Programming Language :: Python :: 3
Classifier: License :: OSI Approved :: MIT License
Classifier: Operating System :: OS Independent
License-File: LICENSE
Requires-Dist: setuptools >=69.1.1
Requires-Dist: SQLAlchemy >=2.0.27
Requires-Dist: pymodm >=0.4.3
Requires-Dist: pymongo >=3.13.0
Requires-Dist: tablib >=3.5.0
Requires-Dist: pymysql >=1.1.0
Requires-Dist: thrift >=0.16.0
Requires-Dist: requests >=2.31.0
Requires-Dist: numpy >=1.26.4
Requires-Dist: pandas >=2.2.1
